pystocky/__init__.py
pystocky/config.py
pystocky/trainer.py
pystocky/data_processor/__init__.py
pystocky/data_processor/dataset.py
pystocky/data_processor/processor.py
pystocky/models/LSTM.py
pystocky/models/__init__.py
pystocky-0.1.dist-info/LICENSE
pystocky-0.1.dist-info/METADATA
pystocky-0.1.dist-info/WHEEL
pystocky-0.1.dist-info/top_level.txt
pystocky-0.1.dist-info/RECORD
