Metadata-Version: 2.1
Name: pystocky
Version: 0.1
Summary: A PyTorch based stock model training and prediction library
Home-page: https://gitee.com/dtsroy/stock-prediction
Author: dtsroy
Author-email: dtsroy39@gmail.com
License: GNU General Public License v3
Classifier: Development Status :: 3 - Alpha
Classifier: Intended Audience :: Developers
Classifier: Topic :: Software Development :: Libraries
Classifier: License :: OSI Approved :: GNU General Public License v3 (GPLv3)
Classifier: Programming Language :: Python :: 3
Requires-Python: >=3.6
License-File: LICENSE
Requires-Dist: torch
Requires-Dist: swanlab
Requires-Dist: pandas
Requires-Dist: scikit-learn
Requires-Dist: numpy
Requires-Dist: tqdm
Requires-Dist: matplotlib
